tasklist_simple/__init__.py
tasklist_simple/cli.py
tasklist_simple/tasks.txt
tasklist_simple-0.1.0.dist-info/METADATA
tasklist_simple-0.1.0.dist-info/WHEEL
tasklist_simple-0.1.0.dist-info/entry_points.txt
tasklist_simple-0.1.0.dist-info/RECORD
