Metadata-Version: 2.3
Name: tasklist-simple
Version: 0.1.0
Summary: Simple task manager via terminal
Author: Bahanna-01
Author-email: bhsantos1424@gmail.com
Requires-Python: >=3.9
Classifier: Programming Language :: Python :: 3
Classifier: Programming Language :: Python :: 3.9
Classifier: Programming Language :: Python :: 3.10
Classifier: Programming Language :: Python :: 3.11
Classifier: Programming Language :: Python :: 3.12
Classifier: Programming Language :: Python :: 3.13
